{
  "name": "下界控制器",
  "appearance": {
    "lightmode": "running",
    "lightlevel": 7,
    "block": "kubejs:machine/nether_controller"
  },
  "components": [
	{
      "mode": "input",
      "id": "input1",
      "capacity": 1,
      "type": "custommachinery:item"
    },
    {
      "mode": "output",
      "id": "output1",
      "type": "custommachinery:item"
    }

  ],
  "gui": [
    {
      "texture": "custommachinery:textures/gui/base_background.png",
      "x": 38,
      "y": 0,
	  "width": 180,
      "type": "custommachinery:texture"
    },
    {
      "x": 47,
      "y": 85,
      "type": "custommachinery:player_inventory"
    },
	{
	  "type": "custommachinery:reset",
      "x": 166,
      "y": 7
    },
    {
      "x": 65,
      "y": 37,
      "type": "custommachinery:slot",
      "id": "input1"
    },  	
    {
      "x": 117,
      "y": 37,
      "type": "custommachinery:progress"
    },
    {
      "x": 200,
      "y": 5,
      "type": "custommachinery:status"
    },
	{
      "id": "output1",
      "x": 173,
      "y": 37,
      "type": "custommachinery:slot"
    },
	{
      "text": "下界控制器",
      "x": 43,
      "y": 7,
      "type": "custommachinery:text"
    }
  ]
}